py_ios/__init__.py
py_ios/execute_cmd.py
py_ios/lib/__init__.py
py_ios/lib/linux/go-ios
py_ios/lib/mac/go-ios
py_ios/lib/windows/go-ios.exe
py_ios/lib/windows/wintun.dll
py_ios-0.1.3.dist-info/METADATA
py_ios-0.1.3.dist-info/WHEEL
py_ios-0.1.3.dist-info/entry_points.txt
py_ios-0.1.3.dist-info/top_level.txt
py_ios-0.1.3.dist-info/RECORD
